{
  "displayName": "FInfiniteScroll",
  "props": {
    "side": {
      "type": "String",
      "default": "end",
      "required": false,
      "description": ""
    },
    "mode": {
      "type": "String",
      "default": "intersect",
      "required": false,
      "description": ""
    },
    "direction": {
      "type": "String",
      "default": "vertical",
      "required": false,
      "description": ""
    },
    "margin": {
      "type": "Number | String",
      "required": false,
      "description": ""
    },
    "color": {
      "type": "String",
      "default": "primary",
      "required": false,
      "description": ""
    },
    "loadMoreText": {
      "type": "String",
      "default": "Load more",
      "required": false,
      "description": ""
    },
    "emptyText": {
      "type": "String",
      "default": "No more items",
      "required": false,
      "description": ""
    },
    "loadingText": {
      "type": "String",
      "default": "Loading more items",
      "required": false,
      "description": ""
    },
    "errorText": {
      "type": "String",
      "default": "Something went wrong",
      "required": false,
      "description": ""
    },
    "retryText": {
      "type": "String",
      "default": "Retry",
      "required": false,
      "description": ""
    },
    "height": {
      "type": "Number | String",
      "required": false,
      "description": ""
    },
    "maxHeight": {
      "type": "Number | String",
      "required": false,
      "description": ""
    },
    "maxWidth": {
      "type": "Number | String",
      "required": false,
      "description": ""
    },
    "minHeight": {
      "type": "Number | String",
      "required": false,
      "description": ""
    },
    "minWidth": {
      "type": "Number | String",
      "required": false,
      "description": ""
    },
    "width": {
      "type": "Number | String",
      "required": false,
      "description": ""
    },
    "tag": {
      "type": "String",
      "default": "div",
      "required": false,
      "description": ""
    },
    "theme": {
      "type": "String",
      "required": false,
      "description": ""
    },
    "class": {
      "type": "String | Array | Object",
      "required": false,
      "description": ""
    },
    "style": {
      "type": "String | Array | Object",
      "default": "null",
      "required": false,
      "description": ""
    }
  },
  "events": {
    "load": {
      "description": ""
    }
  },
  "slots": {}
}
