{
  "displayName": "FSlideGroup",
  "props": {
    "showArrows": {
      "type": "Boolean | String",
      "default": "true",
      "required": false,
      "description": ""
    },
    "centerActive": {
      "type": "Boolean",
      "required": false,
      "description": ""
    },
    "direction": {
      "type": "String",
      "default": "horizontal",
      "required": false,
      "description": ""
    },
    "prevIcon": {
      "type": "String | Object | Function",
      "default": "$prev",
      "required": false,
      "description": ""
    },
    "nextIcon": {
      "type": "String | Object | Function",
      "default": "$next",
      "required": false,
      "description": ""
    },
    "modelValue": {
      "type": "any",
      "required": false,
      "description": ""
    },
    "multiple": {
      "type": "Boolean",
      "required": false,
      "description": ""
    },
    "mandatory": {
      "type": "Boolean | String",
      "required": false,
      "description": ""
    },
    "max": {
      "type": "Number",
      "required": false,
      "description": ""
    },
    "selectedClass": {
      "type": "String",
      "required": false,
      "description": ""
    },
    "theme": {
      "type": "String",
      "required": false,
      "description": ""
    },
    "class": {
      "type": "String | Array | Object",
      "required": false,
      "description": ""
    },
    "style": {
      "type": "String | Array | Object",
      "default": "null",
      "required": false,
      "description": ""
    }
  },
  "events": {
    "update:modelValue": {
      "description": ""
    }
  },
  "slots": {}
}
